{
  "screener_version": 3,
  "trading_date": "20250823",
  "generated_at": "2025-10-26 11:05:59",
  "total_count": 7,
  "criteria": {
    "description": "MA25 이격율 -10% 이하, RSI 30 이하 상향 돌파, MACD(12,26) 상향 돌파"
  },
  "selected_stocks": [
    {
      "code": "175330",
      "name": "JB금융지주",
      "price": 22750.0,
      "change_pct": -1.09,
      "volume": 326459,
      "volume_ratio": 0.75,
      "ma25": 22864.0,
      "price_above_ma25_pct": -0.5,
      "rsi": null,
      "prev_rsi": null,
      "curr_rsi": null,
      "macd": -27.11,
      "macd_signal": -39.69,
      "macd_hist": 12.58,
      "atr": 728.57,
      "trading_strategy": {
        "entry_price": 22750.0,
        "stop_loss": {
          "price": 22067,
          "pct": -3.0,
          "reason": "매수가 대비 -3%"
        },
        "take_profit": [
          {
            "level": 1,
            "price": 22864,
            "pct": 0.5,
            "reason": "MA25 도달",
            "action": "50% 부분 익절"
          },
          {
            "level": 2,
            "price": 24007,
            "pct": 5.53,
            "reason": "MA25 +5% 이격",
            "action": "잔량 전량 익절"
          }
        ],
        "support_line": 21500.0,
        "resistance_line": 25000.0,
        "atr": 728.5714285714286,
        "ma25": 22864.0,
        "risk_reward_ratio": 0.17
      }
    },
    {
      "code": "028260",
      "name": "삼성물산",
      "price": 167200.0,
      "change_pct": 3.15,
      "volume": 351749,
      "volume_ratio": 1.19,
      "ma25": 165844.0,
      "price_above_ma25_pct": 0.82,
      "rsi": null,
      "prev_rsi": null,
      "curr_rsi": null,
      "macd": -1591.01,
      "macd_signal": -1661.4,
      "macd_hist": 70.38,
      "atr": 4382.14,
      "trading_strategy": {
        "entry_price": 167200.0,
        "stop_loss": {
          "price": 162184,
          "pct": -3.0,
          "reason": "매수가 대비 -3%"
        },
        "take_profit": [
          {
            "level": 1,
            "price": 165844,
            "pct": -0.81,
            "reason": "MA25 도달",
            "action": "50% 부분 익절"
          },
          {
            "level": 2,
            "price": 174136,
            "pct": 4.15,
            "reason": "MA25 +5% 이격",
            "action": "잔량 전량 익절"
          }
        ],
        "support_line": 155300.0,
        "resistance_line": 176500.0,
        "atr": 4382.142857142857,
        "ma25": 165844.0,
        "risk_reward_ratio": -0.27
      }
    },
    {
      "code": "011210",
      "name": "현대위아",
      "price": 50600.0,
      "change_pct": 0.4,
      "volume": 32003,
      "volume_ratio": 0.41,
      "ma25": 50114.0,
      "price_above_ma25_pct": 0.97,
      "rsi": null,
      "prev_rsi": null,
      "curr_rsi": null,
      "macd": 339.01,
      "macd_signal": 332.39,
      "macd_hist": 6.63,
      "atr": 1260.71,
      "trading_strategy": {
        "entry_price": 50600.0,
        "stop_loss": {
          "price": 49082,
          "pct": -3.0,
          "reason": "매수가 대비 -3%"
        },
        "take_profit": [
          {
            "level": 1,
            "price": 50114,
            "pct": -0.96,
            "reason": "MA25 도달",
            "action": "50% 부분 익절"
          },
          {
            "level": 2,
            "price": 52619,
            "pct": 3.99,
            "reason": "MA25 +5% 이격",
            "action": "잔량 전량 익절"
          }
        ],
        "support_line": 47400.0,
        "resistance_line": 53700.0,
        "atr": 1260.7142857142858,
        "ma25": 50114.0,
        "risk_reward_ratio": -0.32
      }
    },
    {
      "code": "005830",
      "name": "DB손해보험",
      "price": 131300.0,
      "change_pct": 1.47,
      "volume": 117259,
      "volume_ratio": 0.68,
      "ma25": 129652.0,
      "price_above_ma25_pct": 1.27,
      "rsi": null,
      "prev_rsi": null,
      "curr_rsi": null,
      "macd": 481.67,
      "macd_signal": 368.11,
      "macd_hist": 113.56,
      "atr": 3950.0,
      "trading_strategy": {
        "entry_price": 131300.0,
        "stop_loss": {
          "price": 127361,
          "pct": -3.0,
          "reason": "매수가 대비 -3%"
        },
        "take_profit": [
          {
            "level": 1,
            "price": 129652,
            "pct": -1.26,
            "reason": "MA25 도달",
            "action": "50% 부분 익절"
          },
          {
            "level": 2,
            "price": 136134,
            "pct": 3.68,
            "reason": "MA25 +5% 이격",
            "action": "잔량 전량 익절"
          }
        ],
        "support_line": 121700.0,
        "resistance_line": 134400.0,
        "atr": 3950.0,
        "ma25": 129652.0,
        "risk_reward_ratio": -0.42
      }
    },
    {
      "code": "000270",
      "name": "기아",
      "price": 104800.0,
      "change_pct": 0.87,
      "volume": 553097,
      "volume_ratio": 0.58,
      "ma25": 103072.0,
      "price_above_ma25_pct": 1.68,
      "rsi": null,
      "prev_rsi": null,
      "curr_rsi": null,
      "macd": 934.18,
      "macd_signal": 911.44,
      "macd_hist": 22.74,
      "atr": 1932.14,
      "trading_strategy": {
        "entry_price": 104800.0,
        "stop_loss": {
          "price": 101656,
          "pct": -3.0,
          "reason": "매수가 대비 -3%"
        },
        "take_profit": [
          {
            "level": 1,
            "price": 103072,
            "pct": -1.65,
            "reason": "MA25 도달",
            "action": "50% 부분 익절"
          },
          {
            "level": 2,
            "price": 108225,
            "pct": 3.27,
            "reason": "MA25 +5% 이격",
            "action": "잔량 전량 익절"
          }
        ],
        "support_line": 100500.0,
        "resistance_line": 113200.0,
        "atr": 1932.142857142857,
        "ma25": 103072.0,
        "risk_reward_ratio": -0.55
      }
    },
    {
      "code": "006650",
      "name": "대한유화",
      "price": 103100.0,
      "change_pct": -0.87,
      "volume": 72697,
      "volume_ratio": 2.3,
      "ma25": 100420.0,
      "price_above_ma25_pct": 2.67,
      "rsi": null,
      "prev_rsi": null,
      "curr_rsi": null,
      "macd": 829.1,
      "macd_signal": 823.88,
      "macd_hist": 5.22,
      "atr": 4164.29,
      "trading_strategy": {
        "entry_price": 103100.0,
        "stop_loss": {
          "price": 100007,
          "pct": -3.0,
          "reason": "매수가 대비 -3%"
        },
        "take_profit": [
          {
            "level": 1,
            "price": 100420,
            "pct": -2.6,
            "reason": "MA25 도달",
            "action": "50% 부분 익절"
          },
          {
            "level": 2,
            "price": 105441,
            "pct": 2.27,
            "reason": "MA25 +5% 이격",
            "action": "잔량 전량 익절"
          }
        ],
        "support_line": 94100.0,
        "resistance_line": 109300.0,
        "atr": 4164.285714285715,
        "ma25": 100420.0,
        "risk_reward_ratio": -0.87
      }
    },
    {
      "code": "278470",
      "name": "에이피알",
      "price": 228000.0,
      "change_pct": 4.35,
      "volume": 438097,
      "volume_ratio": 0.63,
      "ma25": 196252.0,
      "price_above_ma25_pct": 16.18,
      "rsi": null,
      "prev_rsi": null,
      "curr_rsi": null,
      "macd": 14609.24,
      "macd_signal": 14525.85,
      "macd_hist": 83.39,
      "atr": 14860.71,
      "trading_strategy": {
        "entry_price": 228000.0,
        "stop_loss": {
          "price": 221160,
          "pct": -3.0,
          "reason": "매수가 대비 -3%"
        },
        "take_profit": [
          {
            "level": 1,
            "price": 196252,
            "pct": -13.92,
            "reason": "MA25 도달",
            "action": "50% 부분 익절"
          },
          {
            "level": 2,
            "price": 206064,
            "pct": -9.62,
            "reason": "MA25 +5% 이격",
            "action": "잔량 전량 익절"
          }
        ],
        "support_line": 165400.0,
        "resistance_line": 239000.0,
        "atr": 14860.714285714286,
        "ma25": 196252.0,
        "risk_reward_ratio": -4.64
      }
    }
  ]
}